basic_data_structure/__init__.py
basic_data_structure/exceptions/__init__.py
basic_data_structure/exceptions/list_exceptions.py
basic_data_structure/exceptions/stack_exceptions.py
basic_data_structure/iterators/__init__.py
basic_data_structure/iterators/list_node_iterator.py
basic_data_structure/iterators/list_value_iterator.py
basic_data_structure/linked_list.py
basic_data_structure/nodes/__init__.py
basic_data_structure/nodes/list_node.py
basic_data_structure/nodes/tree_node.py
basic_data_structure/stack.py
basic_data_structure-0.0.7.dist-info/LICENSE
basic_data_structure-0.0.7.dist-info/METADATA
basic_data_structure-0.0.7.dist-info/WHEEL
basic_data_structure-0.0.7.dist-info/RECORD
