Metadata-Version: 2.3
Name: basic-data-structure
Version: 0.0.7
Summary: Implementation of basic sata structures in Python
License: MIT
Keywords: data structure,data structures,python data structures,basic data structures
Author: Mikhail Shagov
Author-email: mishaga@me.com
Requires-Python: >=3.9,<4.0
Classifier: License :: OSI Approved :: MIT License
Classifier: Programming Language :: Python :: 3
Classifier: Programming Language :: Python :: 3.9
Classifier: Programming Language :: Python :: 3.10
Classifier: Programming Language :: Python :: 3.11
Classifier: Programming Language :: Python :: 3.12
Classifier: Programming Language :: Python :: 3.13
Project-URL: Documentation, https://mishaga.github.io/basic-data-structure/
Project-URL: Issues, https://github.com/mishaga/basic-data-structure/issues
Project-URL: Repository, https://github.com/mishaga/basic-data-structure
